Metadata-Version: 1.1
Name: metabolitics
Version: 0.0.12
Summary: metabolitics
Home-page: https://github.com/MuhammedHasan/metabolitics
Author: Muhammed Hasan Celik
Author-email: hasancelik@std.sehir.edu.tr
License: UNKNOWN
Keywords: bioinformatics,metabolomics,pip-package
Platform: UNKNOWN
Classifier: Programming Language :: Python :: 3.4
Classifier: Programming Language :: Python :: 3.5
Classifier: Programming Language :: Python :: 3.6
